{
    "fleet_id": 5256,
    "fleet_name": "AVTA",
    "vehicle_id": 1,
    "user_name": "nhk",
    "notification_setting_items": [
    {
        "notification_item_id": 32,
        "item_name": "Engine oil",
        "mileage_usage": 1000,
        "date_usage": null,
        "hours_usage": null,
        "usage_count": null,
        "operand": "less-than",
        "usage_value": 20,
        "unit_type": "usage",
        "notificate_type": "Display"
    },
    {
        "notification_item_id": 33,
        "item_name": "Coolant",
        "mileage_usage": 5000,
        "date_usage": null,
        "hours_usage": null,
        "usage_count": null,
        "operand": "greater-than",
        "usage_value": 80,
        "unit_type": "usage",
        "notificate_type": "Display"
    },
    {
        "notification_item_id": 34,
        "item_name": "Front door",
        "mileage_usage": null,
        "date_usage": "20180207",
        "hours_usage": null,
        "usage_count": null,
        "operand": null,
        "usage_value": null,
        "unit_type": null,
        "notificate_type": "Display"
    },
    {
        "notification_item_id": 35,
        "item_name": "Rear door",
        "mileage_usage": null,
        "date_usage": null,
        "hours_usage": null,
        "usage_count": null,
        "operand": "equal",
        "usage_value": 350,
        "unit_type": "count",
        "notificate_type": "Display And Email"
    },
    {
        "notification_item_id": 36,
        "item_name": "High beam",
        "mileage_usage": null,
        "date_usage": null,
        "hours_usage": null,
        "usage_count": null,
        "operand": "less-than_equal-to",
        "usage_value": 80,
        "unit_type": "usage",
        "notificate_type": "Display"
    },
    {
        "notification_item_id": 37,
        "item_name": "Low beam",
        "mileage_usage": null,
        "date_usage": null,
        "hours_usage": null,
        "usage_count": null,
        "operand": "not equal",
        "usage_value": 0,
        "unit_type": "count",
        "notificate_type": "Display And Email"
    }]
}